diff_binom_confint/__init__.py
diff_binom_confint/_applications.py
diff_binom_confint/_binom_confint.py
diff_binom_confint/_confint.py
diff_binom_confint/_diff_binom_confint.py
diff_binom_confint/_utils.py
diff_binom_confint/version.py
diff_binom_confint/_specials/__init__.py
diff_binom_confint/_specials/_wang.py
diff_binom_confint-0.1.0.dist-info/METADATA
diff_binom_confint-0.1.0.dist-info/WHEEL
diff_binom_confint-0.1.0.dist-info/licenses/LICENSE
diff_binom_confint-0.1.0.dist-info/RECORD
