Metadata-Version: 2.4
Name: diff-binom-confint
Version: 0.1.0
Summary: Computation of confidence intervals for binomial proportions and for difference of binomial proportions.
Project-URL: Homepage, https://github.com/DeepPSP/DBCI
Author-email: DeepPSP <wenh06@gmail.com>
License: MIT License
License-File: LICENSE
Classifier: License :: OSI Approved :: MIT License
Classifier: Operating System :: OS Independent
Classifier: Programming Language :: Python
Classifier: Programming Language :: Python :: 3
Classifier: Programming Language :: Python :: 3.6
Classifier: Programming Language :: Python :: 3.7
Classifier: Programming Language :: Python :: 3.8
Classifier: Programming Language :: Python :: 3.9
Classifier: Programming Language :: Python :: 3.10
Classifier: Programming Language :: Python :: 3.11
Classifier: Programming Language :: Python :: 3.12
Requires-Python: >=3.6
Requires-Dist: deprecate-kwargs
Requires-Dist: deprecated
Requires-Dist: jinja2
Requires-Dist: numpy
Requires-Dist: openpyxl
Requires-Dist: pandas
Requires-Dist: scipy
Requires-Dist: tabulate
Provides-Extra: acc
Requires-Dist: numba; extra == 'acc'
Provides-Extra: dev
Requires-Dist: numba; extra == 'dev'
Requires-Dist: pandas; extra == 'dev'
Requires-Dist: pre-commit; extra == 'dev'
Requires-Dist: pytest; extra == 'dev'
Requires-Dist: pytest-cov; extra == 'dev'
Requires-Dist: pytest-xdist; extra == 'dev'
Requires-Dist: rpy2; extra == 'dev'
Requires-Dist: tqdm; extra == 'dev'
Provides-Extra: docs
Requires-Dist: nbsphinx; extra == 'docs'
Requires-Dist: numpydoc; extra == 'docs'
Requires-Dist: pydata-sphinx-theme; extra == 'docs'
Requires-Dist: sphinx-autobuild; extra == 'docs'
Requires-Dist: sphinx-book-theme; extra == 'docs'
Requires-Dist: sphinx-copybutton; extra == 'docs'
Requires-Dist: sphinx-design; extra == 'docs'
Requires-Dist: sphinx-emoji-favicon; extra == 'docs'
Requires-Dist: sphinx-markdown-tables; extra == 'docs'
Requires-Dist: sphinx-multiversion; extra == 'docs'
Requires-Dist: sphinx-rtd-theme; extra == 'docs'
Requires-Dist: sphinx-theme; extra == 'docs'
Requires-Dist: sphinx<7.0; extra == 'docs'
Requires-Dist: sphinxcontrib-bibtex; extra == 'docs'
Requires-Dist: sphinxcontrib-napoleon; extra == 'docs'
Requires-Dist: sphinxcontrib-proof; extra == 'docs'
Requires-Dist: sphinxemoji; extra == 'docs'
Provides-Extra: test
Requires-Dist: pandas; extra == 'test'
Requires-Dist: pre-commit; extra == 'test'
Requires-Dist: pytest; extra == 'test'
Requires-Dist: pytest-cov; extra == 'test'
Requires-Dist: pytest-xdist; extra == 'test'
Requires-Dist: rpy2; extra == 'test'
Requires-Dist: tqdm; extra == 'test'
